quickplot.py
setup.py
Interpolation/Interpolation.py
Interpolation/__init__.py
lquickplot.egg-info/PKG-INFO
lquickplot.egg-info/SOURCES.txt
lquickplot.egg-info/dependency_links.txt
lquickplot.egg-info/top_level.txt