Metadata-Version: 1.0
Name: lquickplot
Version: 0.1.23
Summary: just a simple test
Home-page: UNKNOWN
Author: ap9035
Author-email: ap9035@gmail.com
License: MIT License
Keywords: simple,test
Platform: any
